webp-cli-wrapper/__init__.py
webp-cli-wrapper/webp_cli_wrapper.py
webp_cli_wrapper/__init__.py
webp_cli_wrapper/webp_cli_wrapper.py
WebpCliWrapper-0.1.4.dist-info/LICENSE
WebpCliWrapper-0.1.4.dist-info/METADATA
WebpCliWrapper-0.1.4.dist-info/WHEEL
WebpCliWrapper-0.1.4.dist-info/top_level.txt
WebpCliWrapper-0.1.4.dist-info/RECORD
