Metadata-Version: 2.1
Name: WebpCliWrapper
Version: 0.1.4
Summary: A CLI Wrapper to use webp easily
Home-page: https://gitlab.aptinstall.de/flopana/webp-cli-wrapper
Author: Florian Erbs
Author-email: f@flopana.com
License: MIT
Download-URL: https://pypi.org/project/WebpCliWrapper/
Keywords: webp,webp_cli_wrapper
Platform: UNKNOWN
